aqdlog/__init__.py
aqdlog/py.typed
aqdlog-1.1.0.dist-info/WHEEL
aqdlog-1.1.0.dist-info/METADATA
aqdlog-1.1.0.dist-info/RECORD
