Metadata-Version: 2.3
Name: aqdlog
Version: 1.1.0
Summary: Asynchronous logging with queueing and deduplication
Keywords: logging,async,queue,deduplication,python
Author: Anthony Camilo
Author-email: Anthony Camilo <{ID}+{username}@users.noreply.github.com>
License: MIT
Classifier: Development Status :: 5 - Production/Stable
Classifier: Intended Audience :: Developers
Classifier: License :: OSI Approved :: MIT License
Classifier: Programming Language :: Python
Classifier: Programming Language :: Python :: 3
Classifier: Programming Language :: Python :: 3 :: Only
Classifier: Programming Language :: Python :: 3.8
Classifier: Programming Language :: Python :: 3.9
Classifier: Programming Language :: Python :: 3.10
Classifier: Programming Language :: Python :: 3.11
Classifier: Programming Language :: Python :: 3.12
Classifier: Programming Language :: Python :: 3.13
Classifier: Programming Language :: Python :: 3.14
Classifier: Topic :: System :: Logging
Classifier: Typing :: Typed
Requires-Python: >=3.8
Project-URL: homepage, https://github.com/gargolito/aqdlog
Project-URL: repository, https://github.com/gargolito/aqdlog
